cpp_build/Temperature.dll
cpp_build/temperature.exe
temperature/__init__.py
temperature/temperature.py
temperature-2.7.dist-info/LICENSE
temperature-2.7.dist-info/METADATA
temperature-2.7.dist-info/WHEEL
temperature-2.7.dist-info/top_level.txt
temperature-2.7.dist-info/RECORD
