Metadata-Version: 2.1
Name: temperature
Version: 2.7
Summary: Python module for temperature
Home-page: https://gitlab.com/KD-Group/temperature
Author: WingC, SF Zhou
Author-email: 1018957763@qq.com
License: GPL
Platform: UNKNOWN
Classifier: Development Status :: 3 - Alpha
Classifier: Intended Audience :: Developers
Classifier: License :: OSI Approved :: GNU Affero General Public License v3
Classifier: Programming Language :: Python :: 3
Requires-Python: >=3
